{
  "Padding": {
    "XL": {
      "$extensions": {
        "com.figma.scopes": [
          "ALL_SCOPES"
        ],
        "com.figma.hiddenFromPublishing": false
      },
      "$type": "number",
      "$value": "{Space.11XL}"
    },
    "L": {
      "$extensions": {
        "com.figma.scopes": [
          "ALL_SCOPES"
        ],
        "com.figma.hiddenFromPublishing": false
      },
      "$type": "number",
      "$value": "{Space.7XL}"
    },
    "M": {
      "$extensions": {
        "com.figma.scopes": [
          "ALL_SCOPES"
        ],
        "com.figma.hiddenFromPublishing": false
      },
      "$type": "number",
      "$value": "{Space.4XL}"
    },
    "S": {
      "$extensions": {
        "com.figma.scopes": [
          "ALL_SCOPES"
        ],
        "com.figma.hiddenFromPublishing": false
      },
      "$type": "number",
      "$value": "{Space.2XL}"
    },
    "XS": {
      "$extensions": {
        "com.figma.scopes": [
          "ALL_SCOPES"
        ],
        "com.figma.hiddenFromPublishing": false
      },
      "$type": "number",
      "$value": "{Size.XL}"
    }
  },
  "Device Size": {
    "$extensions": {
      "com.figma.scopes": [
        "ALL_SCOPES"
      ],
      "com.figma.hiddenFromPublishing": false
    },
    "$type": "number",
    "$value": "{Breakpoints.XL}"
  }
}